{"status": "succeeded", "createdDateTime": "2023-01-30T06:10:38Z", "lastUpdatedDateTime": "2023-01-30T06:10:39Z", "analyzeResult": {"version": "3.2.0", "modelVersion": "2022-04-30", "readResults": [{"page": 1, "angle": 88.7636, "width": 564, "height": 423, "unit": "pixel", "lines": [{"boundingBox": [283, 81, 290, 335, 278, 336, 271, 81], "text": "HRA JURTTY REPUBLIC OF INDIA", "appearance": {"style": {"name": "other", "confidence": 0.972}}, "words": [{"boundingBox": [283, 81, 284, 111, 272, 111, 272, 81], "text": "HRA", "confidence": 0.122}, {"boundingBox": [284, 119, 286, 172, 274, 172, 273, 119], "text": "JURTTY", "confidence": 0.071}, {"boundingBox": [286, 186, 288, 253, 276, 253, 274, 186], "text": "REPUBLIC", "confidence": 0.995}, {"boundingBox": [288, 262, 289, 278, 277, 279, 276, 263], "text": "OF", "confidence": 0.997}, {"boundingBox": [289, 289, 290, 330, 278, 331, 277, 290], "text": "INDIA", "confidence": 0.995}]}, {"boundingBox": [262, 160, 262, 170, 255, 170, 255, 160], "text": "P", "appearance": {"style": {"name": "other", "confidence": 0.859}}, "words": [{"boundingBox": [262, 161, 262, 165, 255, 165, 255, 161], "text": "P", "confidence": 0.884}]}, {"boundingBox": [265, 239, 265, 262, 256, 263, 256, 240], "text": "IND", "appearance": {"style": {"name": "other", "confidence": 0.972}}, "words": [{"boundingBox": [265, 239, 265, 256, 256, 256, 256, 239], "text": "IND", "confidence": 0.998}]}, {"boundingBox": [263, 307, 263, 389, 251, 389, 251, 307], "text": "S8270107", "appearance": {"style": {"name": "other", "confidence": 0.972}}, "words": [{"boundingBox": [263, 308, 264, 386, 251, 386, 252, 308], "text": "S8270107", "confidence": 0.97}]}, {"boundingBox": [245, 146, 247, 188, 237, 188, 236, 146], "text": "DANIEL", "appearance": {"style": {"name": "other", "confidence": 0.972}}, "words": [{"boundingBox": [245, 146, 247, 184, 237, 184, 236, 147], "text": "DANIEL", "confidence": 0.994}]}, {"boundingBox": [221, 146, 225, 296, 214, 296, 211, 146], "text": "JANICE GEORGE HAMILTON", "appearance": {"style": {"name": "other", "confidence": 0.972}}, "words": [{"boundingBox": [222, 146, 222, 184, 212, 184, 211, 146], "text": "JANICE", "confidence": 0.997}, {"boundingBox": [222, 191, 223, 231, 214, 231, 213, 191], "text": "GEORGE", "confidence": 0.997}, {"boundingBox": [223, 238, 225, 292, 215, 292, 214, 239], "text": "HAMILTON", "confidence": 0.991}]}, {"boundingBox": [195, 146, 195, 229, 184, 229, 184, 146], "text": "\u092d\u093e\u0930\u0924\u0940\u092f/ INDIAN", "appearance": {"style": {"name": "other", "confidence": 0.972}}, "words": [{"boundingBox": [195, 147, 196, 187, 185, 187, 184, 148], "text": "\u092d\u093e\u0930\u0924\u0940\u092f/", "confidence": 0.922}, {"boundingBox": [196, 189, 195, 225, 185, 225, 185, 189], "text": "INDIAN", "confidence": 0.993}]}, {"boundingBox": [199, 321, 198, 391, 186, 391, 187, 321], "text": "14/02/1981", "appearance": {"style": {"name": "other", "confidence": 0.972}}, "words": [{"boundingBox": [199, 322, 199, 389, 187, 390, 187, 323], "text": "14/02/1981", "confidence": 0.982}]}, {"boundingBox": [178, 145, 179, 229, 170, 229, 169, 145], "text": "www / Place of Birth", "appearance": {"style": {"name": "other", "confidence": 0.972}}, "words": [{"boundingBox": [178, 145, 178, 164, 170, 165, 170, 145], "text": "www", "confidence": 0.795}, {"boundingBox": [179, 177, 179, 179, 170, 179, 170, 177], "text": "/", "confidence": 1}, {"boundingBox": [179, 180, 179, 199, 170, 200, 170, 181], "text": "Place", "confidence": 0.998}, {"boundingBox": [179, 201, 179, 208, 170, 208, 170, 202], "text": "of", "confidence": 1}, {"boundingBox": [179, 209, 179, 227, 171, 228, 170, 210], "text": "Birth", "confidence": 1}]}, {"boundingBox": [166, 145, 169, 284, 159, 284, 156, 145], "text": "RAIPUR, CHHATTISGARH", "appearance": {"style": {"name": "other", "confidence": 0.972}}, "words": [{"boundingBox": [166, 145, 167, 193, 157, 193, 156, 146], "text": "RAIPUR,", "confidence": 0.994}, {"boundingBox": [168, 199, 169, 281, 159, 282, 157, 199], "text": "CHHATTISGARH", "confidence": 0.906}]}, {"boundingBox": [138, 183, 138, 227, 128, 227, 128, 183], "text": "RAIPUR", "appearance": {"style": {"name": "other", "confidence": 0.972}}, "words": [{"boundingBox": [138, 183, 139, 224, 129, 225, 128, 184], "text": "RAIPUR", "confidence": 0.993}]}, {"boundingBox": [130, 20, 142, 20, 142, 33, 131, 33], "text": "7", "appearance": {"style": {"name": "handwriting", "confidence": 0.856}}, "words": [{"boundingBox": [132, 20, 140, 20, 140, 33, 132, 33], "text": "7", "confidence": 0.995}]}, {"boundingBox": [98, 16, 99, 31, 87, 33, 86, 18], "text": "L", "appearance": {"style": {"name": "other", "confidence": 0.945}}, "words": [{"boundingBox": [98, 16, 98, 23, 87, 24, 86, 17], "text": "L", "confidence": 0.9}]}, {"boundingBox": [106, 180, 109, 255, 97, 256, 94, 181], "text": "31/01/2019", "appearance": {"style": {"name": "other", "confidence": 0.972}}, "words": [{"boundingBox": [106, 183, 109, 255, 98, 255, 95, 183], "text": "31/01/2019", "confidence": 0.995}]}, {"boundingBox": [111, 326, 113, 397, 102, 397, 100, 326], "text": "30/01/2029", "appearance": {"style": {"name": "other", "confidence": 0.972}}, "words": [{"boundingBox": [111, 326, 113, 394, 103, 394, 100, 327], "text": "30/01/2029", "confidence": 0.991}]}, {"boundingBox": [64, 7, 78, 406, 62, 406, 49, 8], "text": "P<INDDANIEL << JANICE<GEORGE<HAMILTON <<<<<<<<<", "appearance": {"style": {"name": "other", "confidence": 0.972}}, "words": [{"boundingBox": [64, 8, 67, 105, 52, 105, 50, 8], "text": "P<INDDANIEL", "confidence": 0.964}, {"boundingBox": [67, 108, 67, 124, 53, 124, 52, 108], "text": "<<", "confidence": 0.998}, {"boundingBox": [67, 127, 74, 323, 60, 323, 53, 127], "text": "JANICE<GEORGE<HAMILTON", "confidence": 0.955}, {"boundingBox": [74, 325, 78, 402, 65, 403, 61, 326], "text": "<<<<<<<<<", "confidence": 0.958}]}, {"boundingBox": [39, 7, 55, 405, 39, 406, 24, 8], "text": "S8270107<3IND8102140F2901307 <<<<<<<<<<<<<<< 8", "appearance": {"style": {"name": "other", "confidence": 0.972}}, "words": [{"boundingBox": [40, 7, 48, 261, 34, 261, 24, 8], "text": "S8270107<3IND8102140F2901307", "confidence": 0.902}, {"boundingBox": [48, 264, 54, 392, 40, 393, 34, 264], "text": "<<<<<<<<<<<<<<<", "confidence": 0.939}, {"boundingBox": [54, 395, 55, 404, 41, 404, 41, 396], "text": "8", "confidence": 0.996}]}]}]}}